python_topic_model_preprocessor-0.0.3.dist-info/DESCRIPTION.rst
python_topic_model_preprocessor-0.0.3.dist-info/METADATA
python_topic_model_preprocessor-0.0.3.dist-info/RECORD
python_topic_model_preprocessor-0.0.3.dist-info/WHEEL
python_topic_model_preprocessor-0.0.3.dist-info/metadata.json
python_topic_model_preprocessor-0.0.3.dist-info/top_level.txt
tm_preprocessor/__init__.py
tm_preprocessor/preprocessor.py
tm_preprocessor/utils.py
tm_preprocessor/data/stopwords.csv
